simple_calculator/__init__.py
simple_calculator/simple_calculator.py
simple_calculator_akarni-0.3.0.dist-info/AUTHORS.rst
simple_calculator_akarni-0.3.0.dist-info/LICENSE
simple_calculator_akarni-0.3.0.dist-info/METADATA
simple_calculator_akarni-0.3.0.dist-info/WHEEL
simple_calculator_akarni-0.3.0.dist-info/top_level.txt
simple_calculator_akarni-0.3.0.dist-info/RECORD
