Metadata-Version: 2.1
Name: simple-calculator-akarni
Version: 0.3.0
Summary: A tutorial package to do simple calculations
Home-page: https://github.com/anilkulkarni87/simple_calculator
Author: Anil Kulkarni
Author-email: anil77k@gmail.com
License: MIT license
Keywords: simple_calculator
Classifier: Development Status :: 2 - Pre-Alpha
Classifier: Intended Audience :: Developers
Classifier: License :: OSI Approved :: MIT License
Classifier: Natural Language :: English
Classifier: Programming Language :: Python :: 3
Classifier: Programming Language :: Python :: 3.6
Classifier: Programming Language :: Python :: 3.7
Classifier: Programming Language :: Python :: 3.8
Requires-Python: >=3.6
License-File: LICENSE
License-File: AUTHORS.rst
